shaft_cli/__init__.py
shaft_cli/cli.py
shaft_core-1.0.0.dist-info/METADATA
shaft_core-1.0.0.dist-info/WHEEL
shaft_core-1.0.0.dist-info/entry_points.txt
shaft_core-1.0.0.dist-info/top_level.txt
shaft_core-1.0.0.dist-info/RECORD
