Metadata-Version: 2.4
Name: shaft-core
Version: 1.0.0
Requires-Dist: click
Dynamic: requires-dist
